README
setup.py
Spartacus/Database.py
Spartacus/Report.py
Spartacus/Utils.py
Spartacus/__init__.py
Spartacus.egg-info/PKG-INFO
Spartacus.egg-info/SOURCES.txt
Spartacus.egg-info/dependency_links.txt
Spartacus.egg-info/not-zip-safe
Spartacus.egg-info/requires.txt
Spartacus.egg-info/top_level.txt