Metadata-Version: 2.1
Name: Spartacus
Version: 3.28
Summary: Generic database wrapper
Home-page: http://github.com/wind39/spartacus
Author: William Ivanski
Author-email: william.ivanski@gmail.com
License: MIT
Platform: UNKNOWN
Provides-Extra: oracle
Provides-Extra: mariadb
Provides-Extra: mssql
Provides-Extra: ibmdb2
Provides-Extra: mysql
Provides-Extra: firebird
Provides-Extra: postgresql
Provides-Extra: complete
